ephemeral_postgres
