Metadata-Version: 2.1
Name: ephemeral-postgres
Version: 0.2.0
Summary: Start an ephemeral postgres instance for easy testing
Home-page: https://github.com/jthacker/ephemeral_postgres
Author: jthacker
Author-email: thacker.jon@gmail.com
License: UNKNOWN
Download-URL: https://github.com/jthacker/ephemeral_postgres/archive/v0.2.0.tar.gz
Keywords: postgres,postgresql,testing,docker
Platform: UNKNOWN
Provides-Extra: test
